nightfall/__init__.py
nightfall/alerts.py
nightfall/api.py
nightfall/detection_rules.py
nightfall/exceptions.py
nightfall/findings.py
nightfall-1.4.1.dist-info/LICENSE
nightfall-1.4.1.dist-info/METADATA
nightfall-1.4.1.dist-info/WHEEL
nightfall-1.4.1.dist-info/top_level.txt
nightfall-1.4.1.dist-info/RECORD
