Metadata-Version: 2.1
Name: nightfall
Version: 1.4.1
Summary: Python SDK for Nightfall
Home-page: https://github.com/nightfallai/nightfall-python-sdk
Author: Nightfall
Author-email: support@nightfall.ai
License: MIT
Keywords: nightfall dlp api sdk
Classifier: Development Status :: 5 - Production/Stable
Classifier: Intended Audience :: Developers
Classifier: Intended Audience :: System Administrators
Classifier: License :: OSI Approved :: MIT License
Classifier: Operating System :: OS Independent
Classifier: Topic :: Software Development :: Build Tools
Classifier: Topic :: Software Development :: Libraries :: Python Modules
Classifier: Topic :: Internet
Classifier: Programming Language :: Python :: 3 :: Only
Requires-Python: >=3.7.*
License-File: LICENSE
Requires-Dist: requests
Requires-Dist: urllib3
